mobicontrol/__init__.py
mobicontrol/utils.py
mobicontrol/cli/__init__.py
mobicontrol/cli/apply.py
mobicontrol/cli/apps.py
mobicontrol/cli/policies.py
mobicontrol/client/__init__.py
mobicontrol/client/apps.py
mobicontrol/client/auth.py
mobicontrol/client/policies.py
mobicontrol-1.4.1.dist-info/METADATA
mobicontrol-1.4.1.dist-info/WHEEL
mobicontrol-1.4.1.dist-info/entry_points.txt
mobicontrol-1.4.1.dist-info/top_level.txt
mobicontrol-1.4.1.dist-info/RECORD
