Metadata-Version: 2.1
Name: mobicontrol
Version: 1.4.1
Requires-Dist: Click
Requires-Dist: requests
Requires-Dist: PyYAML
